<?xml version="1.0" encoding="UTF-8" ?>
<!DOCTYPE tiles-definitions PUBLIC
       "-//Apache Software Foundation//DTD Tiles Configuration 2.0//EN"
       "http://tiles.apache.org/dtds/tiles-config_2_0.dtd">
<tiles-definitions>
	<definition name="base.definition"
		template="/WEB-INF/jsp/layout.jsp">
		<put-attribute name="title" value="" />
		<put-attribute name="header" value="/WEB-INF/jsp/topHeader.jsp" />					
		<put-attribute name="body" value="" />
		<put-attribute name="footer" value="/WEB-INF/jsp/footer.jsp" />
	</definition>
	<definition name="home" extends="base.definition">
		<put-attribute name="title" value="Home" />                
		<put-attribute name="body" value="/WEB-INF/jsp/home.jsp" />
	</definition>
        <definition name="login" extends="base.definition">
		<put-attribute name="title" value="Credenciais" />
		<put-attribute name="body" value="/WEB-INF/jsp/login.jsp" />
	</definition>
        <definition name="register" extends="base.definition">
		<put-attribute name="title" value="Registro" />
		<put-attribute name="body" value="/WEB-INF/jsp/register.jsp" />
	</definition>
        <definition name="generator" extends="base.definition">
		<put-attribute name="title" value="Gerador" />
		<put-attribute name="body" value="/WEB-INF/jsp/generator.jsp" />
	</definition>
        <definition name="classes" extends="base.definition">
		<put-attribute name="title" value="Aulas" />
		<put-attribute name="body" value="/WEB-INF/jsp/classes.jsp" />
	</definition>
        <definition name="showClass" extends="base.definition">
		<put-attribute name="title" value="Aulas" />
		<put-attribute name="body" value="/WEB-INF/jsp/showClass.jsp" />
	</definition>
        <definition name="terms" extends="base.definition">
		<put-attribute name="title" value="Termos" />
		<put-attribute name="body" value="/WEB-INF/jsp/terms.jsp" />
	</definition>
	<definition name="contact" extends="base.definition">
		<put-attribute name="title" value="Contact Manager" />
		<put-attribute name="body" value="/WEB-INF/jsp/contact.jsp" />
	</definition>

	<definition name="hello" extends="base.definition">
		<put-attribute name="title" value="TW4R" />                
                            
		<put-attribute name="body" value="/WEB-INF/jsp/hello.jsp" />
	</definition>
                        
        
        <definition name="account" extends="base.definition">
		<put-attribute name="title" value="Conta" />
		<put-attribute name="body" value="/WEB-INF/jsp/account.jsp" />
	</definition>
        <definition name="validate" extends="base.definition">
		<put-attribute name="title" value="Validar Conta" />
		<put-attribute name="body" value="/WEB-INF/jsp/validateAccount.jsp" />
	</definition>
        
        
        <definition name="forgotPassword" extends="base.definition">
		<put-attribute name="title" value="Recuperação de Senha" />
		<put-attribute name="body" value="/WEB-INF/jsp/forgotPassword.jsp" />
	</definition>
        
        
        <definition name="flow" extends="base.definition">
		<put-attribute name="title" value="Sobre" />
		<put-attribute name="body" value="/WEB-INF/jsp/flow.jsp" />
	</definition>
        <definition name="about" extends="base.definition">
		<put-attribute name="title" value="Sobre" />
		<put-attribute name="body" value="/WEB-INF/jsp/about.jsp" />
	</definition>
        <definition name="faq" extends="base.definition">
		<put-attribute name="title" value="FAQ" />
		<put-attribute name="body" value="/WEB-INF/jsp/faq.jsp" />
	</definition>
        <definition name="privacy" extends="base.definition">
		<put-attribute name="title" value="Privacidade" />
		<put-attribute name="body" value="/WEB-INF/jsp/privacy.jsp" />
	</definition>
        <definition name="noOwnerPermission" extends="base.definition">
		<put-attribute name="title" value="Sem Permissão" />
		<put-attribute name="body" value="/WEB-INF/jsp/noOwnerPermission.jsp" />
	</definition>
        <definition name="noAdminPermission" extends="base.definition">
		<put-attribute name="title" value="Sem Permissão" />
		<put-attribute name="body" value="/WEB-INF/jsp/noAdminPermission.jsp" />
	</definition>

</tiles-definitions>